adpkg/__init__.py
adpkg/adcustom.py
adpkg/finance.py
adpkg/triangle.py
adpkg-0.1.4.dist-info/licenses/LICENSE
adpkg-0.1.4.dist-info/METADATA
adpkg-0.1.4.dist-info/WHEEL
adpkg-0.1.4.dist-info/top_level.txt
adpkg-0.1.4.dist-info/RECORD
