Metadata-Version: 2.4
Name: adpkg
Version: 0.1.4
Summary: A beginner-friendly package for advanced mathematical calculations including finance, number theory, strings, matrices, statistics, and geometry.
Author: Amit Dutta
Author-email: amitdutta4255@gmail.com
Maintainer: Amit Dutta
Maintainer-email: amitdutta4255@gmail.com
Project-URL: GitHub, https://github.com/notamitgamer/adpkg
Project-URL: PyPI, https://pypi.org/project/adpkg/
Project-URL: Documentation, https://github.com/notamitgamer/adpkg#readme
Project-URL: Bug Tracker, https://github.com/notamitgamer/adpkg/issues
Project-URL: LinkedIn, https://linkedin.com/in/notamitgamer
Project-URL: Twitter, https://twitter.com/notamitgamer
Project-URL: Instagram, https://instagram.com/notamitgamer
Project-URL: Facebook, https://facebook.com/notamitgamer
Classifier: Programming Language :: Python :: 3
Classifier: License :: OSI Approved :: MIT License
Classifier: Operating System :: OS Independent
Classifier: Intended Audience :: Developers
Classifier: Intended Audience :: Education
Classifier: Intended Audience :: Science/Research
Classifier: Topic :: Education
Classifier: Topic :: Scientific/Engineering :: Mathematics
Requires-Python: >=3.6
License-File: LICENSE
Dynamic: author
Dynamic: author-email
Dynamic: classifier
Dynamic: description
Dynamic: description-content-type
Dynamic: license-file
Dynamic: maintainer
Dynamic: maintainer-email
Dynamic: project-url
Dynamic: requires-python
Dynamic: summary
